foxes_cool/__init__.py
foxes_cool/foxes.py
foxes_cool-1.0.0.dist-info/LICENSE
foxes_cool-1.0.0.dist-info/METADATA
foxes_cool-1.0.0.dist-info/WHEEL
foxes_cool-1.0.0.dist-info/top_level.txt
foxes_cool-1.0.0.dist-info/RECORD
